xyz_media/__init__.py
xyz_media/admin.py
xyz_media/apis.py
xyz_media/apps.py
xyz_media/choices.py
xyz_media/cron.py
xyz_media/forms.py
xyz_media/helper.py
xyz_media/models.py
xyz_media/receivers.py
xyz_media/serializers.py
xyz_media/stats.py
xyz_media/migrations/0001_initial.py
xyz_media/migrations/0002_auto_20200626_0502.py
xyz_media/migrations/0003_remove_image_description.py
xyz_media/migrations/0004_auto_20200809_0023.py
xyz_media/migrations/0005_video_outline.py
xyz_media/migrations/0006_auto_20201020_0202.py
xyz_media/migrations/0007_auto_20210804_0137.py
xyz_media/migrations/0008_audio.py
xyz_media/migrations/0009_video_tags.py
xyz_media/migrations/__init__.py
xyz_media-0.2.1.dist-info/METADATA
xyz_media-0.2.1.dist-info/WHEEL
xyz_media-0.2.1.dist-info/top_level.txt
xyz_media-0.2.1.dist-info/RECORD
